[{
	"省份": "北京市",
	"城市": "北京市",
	"省份code": 110000,
	"城市code": 110000,
	"纳税收入户数": 11,
	"矿山数": 14,
	"销售收入": 30.02551804,
	"税收收入": 2.588292273,
	"减免税额": 0.009059023
},
{
	"省份": "河北省",
	"城市": "保定市",
	"省份code": 130000,
	"城市code": 130600,
	"纳税收入户数": 5,
	"矿山数": 5,
	"销售收入": 2.485464,
	"税收收入": 0.101699,
	"减免税额": 0.000355947
},
{
	"省份": "河北省",
	"城市": "承德市",
	"省份code": 130000,
	"城市code": 130800,
	"纳税收入户数": 4,
	"矿山数": 4,
	"销售收入": 1.49631,
	"税收收入": 0.066251,
	"减免税额": 0.000231879
},
{
	"省份": "河北省",
	"城市": "邯郸市",
	"省份code": 130000,
	"城市code": 130400,
	"纳税收入户数": 12,
	"矿山数": 15,
	"销售收入": 78.365383,
	"税收收入": 3.319796,
	"减免税额": 0.011619286
},
{
	"省份": "河北省",
	"城市": "衡水市",
	"省份code": 130000,
	"城市code": 131100,
	"纳税收入户数": 1,
	"矿山数": 1,
	"销售收入": 0.75,
	"税收收入": 0.02625,
	"减免税额": "9.19E-05"
},
{
	"省份": "河北省",
	"城市": "石家庄市",
	"省份code": 130000,
	"城市code": 130100,
	"纳税收入户数": 5,
	"矿山数": 6,
	"销售收入": 13.453004,
	"税收收入": 0.898697,
	"减免税额": 0.00314544
},
{
	"省份": "河北省",
	"城市": "唐山市",
	"省份code": 130000,
	"城市code": 130200,
	"纳税收入户数": 7,
	"矿山数": 7,
	"销售收入": 96.041521,
	"税收收入": 4.027534,
	"减免税额": 0.014096369
},
{
	"省份": "河北省",
	"城市": "邢台市",
	"省份code": 130000,
	"城市code": 130500,
	"纳税收入户数": 8,
	"矿山数": 8,
	"销售收入": 55.424013,
	"税收收入": 1.058131,
	"减免税额": 0.003703459
},
{
	"省份": "河北省",
	"城市": "张家口市",
	"省份code": 130000,
	"城市code": 130700,
	"纳税收入户数": 3,
	"矿山数": 5,
	"销售收入": 5.175409,
	"税收收入": 0.115978,
	"减免税额": 0.000405923
},
{
	"省份": "天津市",
	"城市": "天津市",
	"省份code": 120000,
	"城市code": 120000,
	"纳税收入户数": 1,
	"矿山数": 1,
	"销售收入": 0,
	"税收收入": 0,
	"减免税额": 0
}
]